Metadata-Version: 2.1
Name: scipystat
Version: 0.2.4
Summary: This is the simplest module for quick work with files.
License: MIT
Requires-Dist: IPython
Requires-Dist: pyperclip
